ict_agent/DigitalHuman.py
ict_agent/Math.py
ict_agent/Public.py
ict_agent/Robot.py
ict_agent/UAV.py
ict_agent/__init__.py
ict_agent/core.py
ict_agent-1.1.0.dist-info/METADATA
ict_agent-1.1.0.dist-info/WHEEL
ict_agent-1.1.0.dist-info/top_level.txt
ict_agent-1.1.0.dist-info/RECORD
