Metadata-Version: 2.1
Name: ict_agent
Version: 1.1.0
Summary: 智能ict三维编程拓展组件
Requires-Dist: websocket-client
